CHANGES
COPYING
MANIFEST.in
README.md
TODO
cbk.py
setup.py
ChordBook.egg-info/PKG-INFO
ChordBook.egg-info/SOURCES.txt
ChordBook.egg-info/dependency_links.txt
ChordBook.egg-info/top_level.txt
chordbook/__init__.py
chordbook/_version.py
chordbook/libcbk.py
chordbook/examples/__init__.py
chordbook/examples/test.cbk
chordbook/output/__init__.py
chordbook/output/_base.py
chordbook/output/html.py
chordbook/output/text.py
chordbook/test/__init__.py
chordbook/test/test_libcbk.py