Metadata-Version: 1.0
Name: ChordBook
Version: 0.0.12
Summary: A tool to manage books of chords for bands.
Home-page: https://github.com/wgmyers/chordbook
Author: Wayne Myers
Author-email: wgmyers@gmail.com
License: COPYING
Platform: UNKNOWN
